cosmonet/__init__.py
cosmonet/cosmonet_classifier.py
cosmonet/cosmonet_pinn.py
cosmonet/cosmonet_xai.py
cosmonet/quick_start.py
cosmonet/testttttt_best_one_accuracy.py
cosmonet-0.1.0.dist-info/METADATA
cosmonet-0.1.0.dist-info/WHEEL
cosmonet-0.1.0.dist-info/license.txt
cosmonet-0.1.0.dist-info/top_level.txt
cosmonet-0.1.0.dist-info/RECORD
