Metadata-Version: 2.1
Name: cosmonet
Version: 0.1.0
Summary: Astronomical Light Curve Classification using Physics-Informed Neural Networks
Home-page: https://github.com/cosmonet-team/cosmonet
Author: CosmoNet Team
Author-email: cosmonet-team@example.com
License: Apache 2.0
Project-URL: Bug Reports, https://github.com/cosmonet-team/cosmonet/issues
Project-URL: Source, https://github.com/cosmonet-team/cosmonet
Project-URL: Documentation, https://cosmonet.readthedocs.io/
Keywords: astronomy,machine-learning,neural-networks,light-curves,classification
Platform: UNKNOWN
Classifier: Development Status :: 3 - Alpha
Classifier: Intended Audience :: Science/Research
Classifier: License :: OSI Approved :: Apache Software License
Classifier: Programming Language :: Python :: 3
Classifier: Programming Language :: Python :: 3.8
Classifier: Programming Language :: Python :: 3.9
Classifier: Programming Language :: Python :: 3.10
Classifier: Programming Language :: Python :: 3.11
Classifier: Topic :: Scientific/Engineering :: Astronomy
Requires-Python: >=3.8
License-File: license.txt
Requires-Dist: numpy>=1.21.0
Requires-Dist: pandas>=1.3.0
Requires-Dist: matplotlib>=3.5.0
Requires-Dist: seaborn>=0.11.0
Requires-Dist: scikit-learn>=1.0.0
Requires-Dist: tensorflow>=2.8.0
Requires-Dist: astropy>=5.0.0
Requires-Dist: scipy>=1.7.0
Requires-Dist: tqdm>=4.62.0
